Workbook

Sheet 01_Overview_&_Scope
A1: STANDARD COSTING & VARIANCE ANALYSIS
A2: Relaxo Footwears Limited | Illustrative footwear manufacturing case study | CMA portfolio project
A4: PROJECT PROFILE
A5: Company context | B5: Relaxo Footwears Limited
A6: Industry | B6: Footwear manufacturing
A7: Product scope | B7: Illustrative EVA/rubber-based slipper or sandal product family
A8: Analysis period | B8: Illustrative monthly production period - 1 Month (25 Operating Days)
A9: Direct Material Cost Pools | B9: EVA & Natural Rubber
A10: Direct Labour Grades | B10: Skilled & Semi-Skilled Labour
A11: Manufacturing Overheads | B11: Variable (Power) & Fixed (Plant)
A12: Model type | B12: Standard costing and variance analysis case study
A13: Planned production | B13: 100,000 pairs
A14: Actual production | B14: 96,000 pairs
A16: PROJECT OBJECTIVE
A17: Build a transparent, formula-driven standard costing model for an illustrative footwear product family; compare actual inputs with standards allowed for actual output; quantify key variances; and prioritise practical management investigations.
A20: IMPORTANT DATA NOTE
A21: Public information is used only for company and industry context. Detailed material specifications, production volumes, standard prices, labour hours/rates and factory overhead figures are illustrative assumptions for learning. They are NOT Relaxo's actual internal production or cost data. This simplified case study is not intended to represent one exact Relaxo SKU.
A24: Sources
A25: NSE Q4 & FY26 Investor Presentation
A26: View Relaxo Annual Report 2026
A28: WORKBOOK COLOUR-CODING
A29: Blue Text | B29: Hardcoded Inputs (Tiers 1, 2 & 3)
A30: Black Text | B30: Same-Sheet Dynamic Formulas
A31: Green Text | B31: Cross-Sheet Formula Links
A32: Green Badge / Red Badge | B32: Variance Direction & Audit Status

Sheet 02_Assumptions
A1: Illustrative Assumptions
A3: Financial/Operational Metric | B3: Unit | C3: FY25 | D3: FY26 | E3: YOY Change %
A4: Number of Pairs sold | B4: Cr Pairs | C4: 17.8 | D4: 17.5 | E4: =D4/C4-1 -> -0.016853933
A5: Average Realization per pair | B5: ₹/pair | C5: 156 | D5: 153 | E5: =D5/C5-1 -> -0.019230769
A6: Revenue from Operations | B6: ₹ Crore | C6: 2789.61 | D6: 2702.16 | E6: =D6/C6-1 -> -0.031348468
A7: Cost of Materials Consumed (incl. Packing) | B7: ₹ Crore | C7: 1037.83 | D7: 990.96 | E7: =D7/C7-1 -> -0.045161539
A8: Purchases of Stock-in-Trade | B8: ₹ Crore | C8: 105.57 | D8: 106.06 | E8: =D8/C8-1 -> 0.0046414701
A9: Changes in Inventories of FG, SIT & WIP | B9: ₹ Crore | C9: 5.53 | D9: 6.01 | E9: =D9/C9-1 -> 0.086799277
A10: Employee Benefits Expense | B10: ₹ Crore | C10: 400.55 | D10: 411.81 | E10: =D10/C10-1 -> 0.028111347
A11: Depreciation & Amortisation Expense | B11: ₹ Crore | C11: 158.43 | D11: 157.2 | E11: =D11/C11-1 -> -0.0077636811
A12: Other Expenses (Factory OH + SG&A) | B12: ₹ Crore | C12: 858.13 | D12: 813.34 | E12: =D12/C12-1 -> -0.052194889
A13: EBITDA | B13: ₹ Crore | C13: 382 | D13: 373.98 | E13: =D13/C13-1 -> -0.020994764
A14: Gross Revenue per Pair sold | B14: ₹/pair | C14: =C6/C4 -> 156.71966 | D14: =D6/D4 -> 154.40914 | E14: =D14/C14-1 -> -0.014743013
A15: Material & Packing Cost per Pair | B15: ₹/pair | C15: =C7/C4 -> 58.305056 | D15: =D7/D4 -> 56.626286 | E15: =D15/C15-1 -> -0.02879288
A16: Material Cost as % of Revenue | B16: % | C16: =C7/C6 -> 0.37203408 | D16: =D7/D6 -> 0.36672884 | E16: =D16/C16-1 -> -0.014260103
A17: Employee Cost per Pair Sold | B17: ₹/pair | C17: =C10/C4 -> 22.502809 | D17: =D10/D4 -> 23.532 | E17: =D17/C17-1 -> 0.045736113
A18: Depreciation per Pair Sold | B18: ₹/pair | C18: =C11/C4 -> 8.9005618 | D18: =D11/D4 -> 8.9828571 | E18: =D18/C18-1 -> 0.0092460843
A21: STANDARD ASSUMPTIONS
A22: Code | B22: Standard Cost Parameter / Input Variable | C22: Proposed Value | D22: Unit | E22: Data Classification | F22: Simple Basis/ Reason
A23: STD_VOL | B23: Budgeted / Normal Monthly Production Output | C23: 100000 | D23: Pairs / Month | E23: Model Assumption | F23: 4,000 pairs/day × 25 working days. Used as the normal output for the selected production line.
A24: ACT_VOL | B24: Actual Monthly Production Output | C24: 96000 | D24: Pairs / Month | E24: Model Assumption | F24: 24 working days × 4,000 pairs/day = 96,000 pairs (96% capacity utilization) due to 1 day of unplanned mould-heater downtime.
A25: DM1_QTY | B25: DM-1: EVA Compound — Std Qty | C25: 0.22 | D25: kg / Pair | E25: Model Assumption | F25: Assumed EVA material required to produce one finished pair, including normal production loss.
A26: DM1_PRC | B26: DM-1: EVA Compound — Std Price | C26: 105 | D26: ₹ / kg | E26: Commodity Benchmark | F26: Assumed expected purchase price for EVA compound during the period.
A27: DM2_QTY | B27: DM-2:Natural/synthetic rubber compound — Std Qty | C27: 0.09 | D27: kg / Pair | E27: Model Assumption | F27: Assumed rubber compound required to produce one finished pair, including normal production loss.
A28: DM2_PRC | B28: DM-2: Natural/synthetic rubber compound — Std Price | C28: 195 | D28: ₹ / kg | E28: Commodity Benchmark | F28: Assumed expected purchase price for the rubber compound during the period.
A29: DL1_HRS | B29: DL-1: Skilled Compounding & Moulding — Std Hours | C29: 0.04 | D29: Hours / Pair | E29: Model Assumption | F29: Assumed direct labour time per pair.
A30: DL1_RTE | B30: DL-1: Skilled Compounding & Moulding Operator — Std Wage Rate | C30: 110 | D30: ₹ / Hour | E30: Wage Benchmark | F30: Assumed hourly rate for skilled production labour.
A31: DL2_HRS | B31: DL-2: Semi-Skilled Trimming, Strap & Packing — Std Hours | C31: 0.08 | D31: Hours / Pair | E31: Model Assumption | F31: 4.8 minutes per pair.
A32: DL2_RTE | B32: DL-2: Semi-Skilled Assembly Worker — Std Wage Rate | C32: 95 | D32: ₹ / Hour | E32: Wage Benchmark | F32: Assumed semi-skilled production labour rate.
A33: VMOH_RATE | B33: VMOH: Factory Power & Utilities Rate per DLH | C33: 37.5 | D33: ₹ / DLH | E33: Model Assumption | F33: Allocation rate based on estimated factory power and utility costs.
A34: FMOH_BUD | B34: FMOH: Budgeted Monthly Fixed Manufacturing Overhead | C34: 660000 | D34: ₹ / Month | E34: Model Assumption | F34: Fixed factory costs such as depreciation, maintenance and factory supervision.

Sheet 03_Standard_Cost
A1: STANDARD ABSORPTION COST SHEET (PER PAIR & MONTHLY BUDGET)
A3: Normal Monthly Capacity (Pairs): | C3: ='02_Assumptions'!C23 -> 100000 | D3: Standard Direct Labour Hours / Pair: | F3: 0.12 | G3: Budgeted Monthly DLH: | I3: 12000
A5: Cost Code | B5: Cost Element | C5: Input Unit | D5: Standard Qty / Hrs per Pair (SQ / SH) | E5: Standard Qty / Hrs for 100000 Pairs (SQ / SH) | F5: Standard Price / Rate per Unit (SP / SR) | G5: Standard Cost per Pair (₹ / Pair) | H5: Monthly Standard Cost (1,00,000 Pairs) (₹) | I5: % Share of Standard Factory Cost
A6: DM-1 | B6: EVA Compound | C6: Kg | D6: ='02_Assumptions'!C25 -> 0.22 | E6: =D6*$C$3 -> 22000 | F6: ='02_Assumptions'!C26 -> 105 | G6: =D6*F6 -> 23.1 | H6: =E6*F6 -> 2310000 | I6: =G6/$G$17 -> 0.36235294
A7: DM-2 | B7: Natural/synthetic rubber compound | C7: Kg | D7: ='02_Assumptions'!C27 -> 0.09 | E7: =D7*$C$3 -> 9000 | F7: ='02_Assumptions'!C28 -> 195 | G7: =D7*F7 -> 17.55 | H7: =E7*F7 -> 1755000 | I7: =G7/$G$17 -> 0.27529412
A8: TOT-DM | B8: Total Standard Direct Material Cost (A) | C8: Pair | D8: =SUM(D6:D7) -> 0.31 | E8: =SUM(E6:E7) -> 31000 | F8: =H8/E8 -> 131.12903 | G8: =SUM(G6:G7) -> 40.65 | H8: =SUM(H6:H7) -> 4065000 | I8: =G8/$G$17 -> 0.63764706
A9: DL-1 | B9: Skilled Compounding & Moulding Machine Operators | C9: DLH | D9: ='02_Assumptions'!C29 -> 0.04 | E9: =D9*$C$3 -> 4000 | F9: ='02_Assumptions'!C30 -> 110 | G9: =D9*F9 -> 4.4 | H9: =E9*F9 -> 440000 | I9: =G9/$G$17 -> 0.069019608
A10: DL-2 | B10: Semi-Skilled Trimming, Strap Assembly & Packing Workers | C10: DLH | D10: ='02_Assumptions'!C31 -> 0.08 | E10: =D10*$C$3 -> 8000 | F10: ='02_Assumptions'!C32 -> 95 | G10: =D10*F10 -> 7.6 | H10: =E10*F10 -> 760000 | I10: =G10/$G$17 -> 0.11921569
A11: TOT-DL | B11: Total Standard Direct Labour Cost (B) | C11: DLH | D11: =SUM(D9:D10) -> 0.12 | E11: =SUM(E9:E10) -> 12000 | F11: =H11/E11 -> 100 | G11: =SUM(G9:G10) -> 12 | H11: =SUM(H9:H10) -> 1200000 | I11: =G11/$G$17 -> 0.18823529
A12: PRIME | B12: Standard Prime Cost per Pair (A + B) | C12: Pair | D12: 0 | E12: 0 | F12: 0 | G12: =SUM(G11,G8) -> 52.65 | H12: =SUM(H11,H8) -> 5265000 | I12: =G12/$G$17 -> 0.82588235
A13: VMOH | B13: Variable Manufacturing Overhead (Factory Power & Moulding Utilities) | C13: DLH | D13: =D11 -> 0.12 | E13: =D13*$C$3 -> 12000 | F13: ='02_Assumptions'!C33 -> 37.5 | G13: =D13*F13 -> 4.5 | H13: =E13*F13 -> 450000 | I13: =G13/$G$17 -> 0.070588235
A14: FMOH | B14: Fixed Manufacturing Overhead (Press/Mould Depr, Demand Charge & Supervision) | C14: DLH | D14: =D11 -> 0.12 | E14: =D14*$C$3 -> 12000 | F14: =H14/E14 -> 55 | G14: =H14/C3 -> 6.6 | H14: ='02_Assumptions'!C34 -> 660000 | I14: =G14/$G$17 -> 0.10352941
A15: TOT-MOH | B15: Total Standard Manufacturing Overhead (C = VMOH + FMOH) | C15: DLH | D15: =D14 -> 0.12 | E15: =E14 -> 12000 | F15: =H15/E15 -> 92.5 | G15: =SUM(G13:G14) -> 11.1 | H15: =SUM(H13:H14) -> 1110000 | I15: =G15/$G$17 -> 0.17411765
A16: VAR-COST | B16: Standard Variable / Marginal Factory Cost per Pair (DM + DL + VMOH) | C16: Pair | D16: 0 | E16: 0 | F16: 0 | G16: =G12+G13 -> 57.15 | H16: =H12+H13 -> 5715000 | I16: =G16/$G$17 -> 0.89647059
A17: STD-TOT | B17: TOTAL STANDARD FACTORY COST OF PRODUCTION (A + B + C) | C17: Pair | D17: 0 | E17: 0 | F17: 0 | G17: =G12+G15 -> 63.75 | H17: =H12+H15 -> 6375000 | I17: =G17/$G$17 -> 1

Sheet 04_Actual_Production_&_Costs
A1: ACTUAL PRODUCTION & COST SHEET
A2: MONTHLY STANDARD COST ALLOWED (FOR 96,000 PAIRS) VS. ACTUAL PRODUCTION COSTS
A4: Normal Monthly Capacity (Pairs): | C4: ='02_Assumptions'!C23 -> 100000 | D4: Actual Output Produced (Pairs): | F4: ='02_Assumptions'!C24 -> 96000 | G4: Capacity Utilization | I4: =F4/C4 -> 0.96
A6: Cost Code | B6: Cost Element | C6: Unit | D6: Std Qty / Hrs Allowed for Actual production (SQ / SH) | E6: Standard Price / Rate (SP / SR) (₹) | F6: Standard Cost Absorbed (₹) | G6: Actual Qty / Hrs (AQ / AH) | H6: Actual Price / Rate Paid (AP / AR) (₹) | I6: Actual Total Cost (₹)
A7: DM-1 | B7: EVA Compound | C7: Kg | D7: ='03_Standard_Cost'!D6*'04_Actual_Production_&_Costs'!$F$4 -> 21120 | E7: ='03_Standard_Cost'!F6 -> 105 | F7: =D7*E7 -> 2217600 | G7: 22050 | H7: 102 | I7: =G7*H7 -> 2249100
A8: DM-2 | B8: Natural/synthetic rubber compound | C8: Kg | D8: ='03_Standard_Cost'!D7*'04_Actual_Production_&_Costs'!$F$4 -> 8640 | E8: ='03_Standard_Cost'!F7 -> 195 | F8: =D8*E8 -> 1684800 | G8: 8450 | H8: 208 | I8: =G8*H8 -> 1757600
A9: TOT-DM | B9: Total Direct Material Cost (A) | C9: Kg | D9: =SUM(D7:D8) -> 29760 | E9: =F9/D9 -> 131.12903 | F9: =SUM(F7:F8) -> 3902400 | G9: =SUM(G7:G8) -> 30500 | H9: =I9/G9 -> 131.36721 | I9: =SUM(I7:I8) -> 4006700
A10: DL-1 | B10: Skilled Compounding & Moulding Machine Operators | C10: DLH | D10: ='03_Standard_Cost'!D9*'04_Actual_Production_&_Costs'!$F$4 -> 3840 | E10: ='03_Standard_Cost'!F9 -> 110 | F10: =D10*E10 -> 422400 | G10: 3960 | H10: 114 | I10: =G10*H10 -> 451440
A11: DL-2 | B11: Semi-Skilled Trimming, Strap Assembly & Packing Workers | C11: DLH | D11: ='03_Standard_Cost'!D10*'04_Actual_Production_&_Costs'!$F$4 -> 7680 | E11: ='03_Standard_Cost'!F10 -> 95 | F11: =D11*E11 -> 729600 | G11: 8100 | H11: 92 | I11: =G11*H11 -> 745200
A12: TOT-DL | B12: Total Direct Labour Cost (B) | C12: DLH | D12: =SUM(D10:D11) -> 11520 | E12: =F12/D12 -> 100 | F12: =SUM(F10:F11) -> 1152000 | G12: =SUM(G10:G11) -> 12060 | H12: =I12/G12 -> 99.223881 | I12: =SUM(I10:I11) -> 1196640
A13: PRIME | B13: Prime Cost per Pair (A + B) | C13: Pair | D13: 0 | E13: 0 | F13: =F9+F12 -> 5054400 | G13: 0 | H13: 0 | I13: =I9+I12 -> 5203340
A14: VMOH | B14: Variable Manufacturing Overhead (Factory Power & Moulding Utilities) | C14: DLH | D14: =D12 -> 11520 | E14: ='03_Standard_Cost'!F13 -> 37.5 | F14: =D14*E14 -> 432000 | G14: =G12 -> 12060 | H14: 38.5 | I14: =G14*H14 -> 464310
A15: FMOH | B15: Fixed Manufacturing Overhead (Press/Mould Depr, Demand Charge & Supervision) | C15: DLH | D15: =D12 -> 11520 | E15: ='03_Standard_Cost'!F14 -> 55 | F15: =D15*E15 -> 633600 | G15: =G12 -> 12060 | H15: =I15/G15 -> 55.721393 | I15: 672000
A16: TOT-MOH | B16: Total Manufacturing Overhead (C = VMOH + FMOH) | C16: DLH | D16: =D12 -> 11520 | E16: =F16/D16 -> 92.5 | F16: =SUM(F14:F15) -> 1065600 | G16: =G12 -> 12060 | H16: =I16/G16 -> 94.221393 | I16: =SUM(I14:I15) -> 1136310
A17: VAR-COST | B17: Total Variable Manufacturing Cost (DM + DL + VMOH) | C17: Pair | D17: 0 | E17: 0 | F17: =F13+F14 -> 5486400 | G17: 0 | H17: 0 | I17: =I13+I14 -> 5667650
A18: ACT-TOT | B18: TOTAL MANUFACTURING COST OF ACTUAL OUTPUT (A + B + C) | C18: Pair | D18: 0 | E18: 0 | F18: =F13+F16 -> 6120000 | G18: 0 | H18: 0 | I18: =I13+I16 -> 6339650

Sheet 05_Variance_Analysis
A1: VARIANCE ANALYSIS — MATERIAL, LABOUR & MANUFACTURING OVERHEAD
A2: Positive variance = Favourable (F); Negative variance = Adverse (A). All amounts relate to 96,000 pairs.
A4: 1. DIRECT MATERIAL PRICE, USAGE & TOTAL COST VARIANCES
A5: Cost Code | B5: Direct Material Category | C5: Std Cost (SQ × SP) (₹) | D5: Actual Qty @ Std Price (AQ × SP) (₹) | E5: Actual Cost (AQ × AP) (₹) | F5: Material Price Variance (MPV) = (SP - AP) × AQ | G5: Material Usage Variance (MUV) = (SQ - AQ) × SP | H5: Total Material Variance (MCV) = MPV + MUV | I5: Direction (F / A)
A6: DM-1 | B6: EVA Compound | C6: ='04_Actual_Production_&_Costs'!F7 -> 2217600 | D6: ='04_Actual_Production_&_Costs'!G7*'04_Actual_Production_&_Costs'!E7 -> 2315250 | E6: ='04_Actual_Production_&_Costs'!I7 -> 2249100 | F6: =D6-E6 -> 66150 | G6: =C6-D6 -> -97650 | H6: =F6+G6 -> -31500 | I6: =IF(H6>0,"Favourable (F)","Adverse (A)") -> Adverse (A)
A7: DM-2 | B7: Natural/synthetic rubber compound | C7: ='04_Actual_Production_&_Costs'!F8 -> 1684800 | D7: ='04_Actual_Production_&_Costs'!G8*'04_Actual_Production_&_Costs'!E8 -> 1647750 | E7: ='04_Actual_Production_&_Costs'!I8 -> 1757600 | F7: =D7-E7 -> -109850 | G7: =C7-D7 -> 37050 | H7: =F7+G7 -> -72800 | I7: =IF(H7>0,"Favourable (F)","Adverse (A)") -> Adverse (A)
A8: TOT-DM | B8: Total Direct Material Cost Variances | C8: =SUM(C6:C7) -> 3902400 | D8: =SUM(D6:D7) -> 3963000 | E8: =SUM(E6:E7) -> 4006700 | F8: =SUM(F6:F7) -> -43700 | G8: =SUM(G6:G7) -> -60600 | H8: =SUM(H6:H7) -> -104300 | I8: =IF(H8>0,"Favourable (F)","Adverse (A)") -> Adverse (A)
A11: 2. DIRECT LABOUR RATE, EFFICIENCY & TOTAL LABOUR VARIANCES
A12: Cost Code | B12: Direct Labour Grade | C12: Std Cost (SH × SR) (₹) | D12: Actual Hrs @ Std Rate (AH × SR) (₹) | E12: Actual Labour Cost (AH × AR) (₹) | F12: Labour Rate Variance (LRV) = (SR - AR) × AH | G12: Labour Efficiency Variance (LEV) = (SH - AH) × SR | H12: Total Labour Variance (LCV) = LRV + LEV | I12: Direction (F / A)
A13: DL-1 | B13: Skilled Compounding & Moulding Machine Operators | C13: ='04_Actual_Production_&_Costs'!F10 -> 422400 | D13: ='04_Actual_Production_&_Costs'!G10*'04_Actual_Production_&_Costs'!E10 -> 435600 | E13: ='04_Actual_Production_&_Costs'!I10 -> 451440 | F13: =D13-E13 -> -15840 | G13: =C13-D13 -> -13200 | H13: =F13+G13 -> -29040 | I13: =IF(H13>0,"Favourable (F)","Adverse (A)") -> Adverse (A)
A14: DL-2 | B14: Semi-Skilled Trimming, Strap Assembly & Packing Workers | C14: ='04_Actual_Production_&_Costs'!F11 -> 729600 | D14: ='04_Actual_Production_&_Costs'!G11*'04_Actual_Production_&_Costs'!E11 -> 769500 | E14: ='04_Actual_Production_&_Costs'!I11 -> 745200 | F14: =D14-E14 -> 24300 | G14: =C14-D14 -> -39900 | H14: =F14+G14 -> -15600 | I14: =IF(H14>0,"Favourable (F)","Adverse (A)") -> Adverse (A)
A15: TOT-DL | B15: Total Direct Labour Cost Variances | C15: =SUM(C13:C14) -> 1152000 | D15: =SUM(D13:D14) -> 1205100 | E15: =SUM(E13:E14) -> 1196640 | F15: =SUM(F13:F14) -> 8460 | G15: =SUM(G13:G14) -> -53100 | H15: =SUM(H13:H14) -> -44640 | I15: =IF(H15>0,"Favourable (F)","Adverse (A)") -> Adverse (A)
A18: 3. VARIABLE & FIXED MANUFACTURING OVERHEAD VARIANCES
A19: Cost Code | B19: Manufacturing Overhead Pool | C19: Absorbed Std OH (SH × SR) (₹) | D19: Budgeted Benchmark (₹) | E19: Actual OH Incurred (₹) | F19: OH Expenditure Variance (VOEV / FOEV) | G19: OH Efficiency/Volume Variance (VOEfV / FOVV) | H19: Total Overhead Cost Variance | I19: Direction (F / A)
A20: VMOH | B20: Variable overhead — power & utilities | C20: ='04_Actual_Production_&_Costs'!F14 -> 432000 | D20: ='04_Actual_Production_&_Costs'!G14*'04_Actual_Production_&_Costs'!E14 -> 452250 | E20: ='04_Actual_Production_&_Costs'!I14 -> 464310 | F20: =D20-E20 -> -12060 | G20: =C20-D20 -> -20250 | H20: =G20+F20 -> -32310 | I20: =IF(H20>0,"Favourable (F)","Adverse (A)") -> Adverse (A)
A21: FMOH | B21: Fixed overhead — depreciation, demand charges & supervision | C21: ='04_Actual_Production_&_Costs'!F15 -> 633600 | D21: ='03_Standard_Cost'!H14 -> 660000 | E21: ='04_Actual_Production_&_Costs'!I15 -> 672000 | F21: =D21-E21 -> -12000 | G21: =C21-D21 -> -26400 | H21: =G21+F21 -> -38400 | I21: =IF(H21>0,"Favourable (F)","Adverse (A)") -> Adverse (A)
A22: TOT-MOH | B22: Total Manufacturing Overhead Variances | C22: =SUM(C20:C21) -> 1065600 | D22: =SUM(D20:D21) -> 1112250 | E22: =SUM(E20:E21) -> 1136310 | F22: =SUM(F20:F21) -> -24060 | G22: =SUM(G20:G21) -> -46650 | H22: =SUM(H20:H21) -> -70710 | I22: =IF(H22>0,"Favourable (F)","Adverse (A)") -> Adverse (A)
A25: 4. FIXED OVERHEAD VOLUME VARIANCE DECOMPOSITION (CAPACITY vs. EFFICIENCY)
A26: Sub-Variance Code | B26: FMOH Volume Sub-Component | C26: Absorbed Hours (SH = 11,520) | D26: Budgeted Hours (BH = 12,000) | E26: Actual Hours (AH = 12,060) | F26: FMOH Capacity Variance = (AH - BH) × SR | G26: FMOH Efficiency Variance = (SH - AH) × SR | H26: Total FMOH Volume Variance = Cap + Eff | I26: Direction (F / A)
A27: FMOH-VOL | B27: Fixed Overhead Volume Breakdown (@ ₹55.00 / Standard DLH) | C27: ='04_Actual_Production_&_Costs'!D15 -> 11520 | D27: ='03_Standard_Cost'!I3 -> 12000 | E27: ='04_Actual_Production_&_Costs'!G15 -> 12060 | F27: =(E27-D27)*'03_Standard_Cost'!F14 -> 3300 | G27: =(C27-E27)*'03_Standard_Cost'!F14 -> -29700 | H27: =F27+G27 -> -26400 | I27: =IF(H27>0,"Favourable (F)","Adverse (A)") -> Adverse (A)

Sheet 06_Reconciliation_&_Controls
A1: COST RECONCILIATION STATEMENT & AUDIT CONTROLS
A3: 1. STANDARD-TO-ACTUAL COST RECONCILIATION (96,000 PAIRS)
A4: Code | B4: Variance / Reconciliation Line | C4: Category | D4: Variance: Favourable (+) / Adverse (-) (₹) | E4: Cost after adjustment (₹) | F4: Impact per pair (₹) | G4: % of Standard Cost | H4: Status
A5: STD-COST | B5: Standard cost for actual output | C5: Standard cost | D5: 0 | E5: ='04_Actual_Production_&_Costs'!F18 -> 6120000 | F5: =E5/'04_Actual_Production_&_Costs'!$F$4 -> 63.75 | G5: =E5/E5 -> 1 | H5: 0
A6: MPV-DM1 | B6: Direct Material Price Variance — EVA Compound | C6: Direct material | D6: ='05_Variance_Analysis'!F6 -> 66150 | E6: =E5-D6 -> 6053850 | F6: =D6/'04_Actual_Production_&_Costs'!$F$4 -> 0.6890625 | G6: =D6/$E$5 -> 0.010808824 | H6: =IF(D6>=0,"Favourable (F)","Adverse (A)") -> Favourable (F)
A7: MUV-DM1 | B7: Direct Material Usage Variance — EVA Compound | C7: Direct material | D7: ='05_Variance_Analysis'!G6 -> -97650 | E7: =E6-D7 -> 6151500 | F7: =D7/'04_Actual_Production_&_Costs'!$F$4 -> -1.0171875 | G7: =D7/$E$5 -> -0.015955882 | H7: =IF(D7>=0,"Favourable (F)","Adverse (A)") -> Adverse (A)
A8: MPV-DM2 | B8: Direct Material Price Variance — Natural/synthetic rubber compound | C8: Direct material | D8: ='05_Variance_Analysis'!F7 -> -109850 | E8: =E7-D8 -> 6261350 | F8: =D8/'04_Actual_Production_&_Costs'!$F$4 -> -1.1442708 | G8: =D8/$E$5 -> -0.017949346 | H8: =IF(D8>=0,"Favourable (F)","Adverse (A)") -> Adverse (A)
A9: MUV-DM2 | B9: Direct Material Usage Variance — Natural/synthetic rubber compound | C9: Direct material | D9: ='05_Variance_Analysis'!G7 -> 37050 | E9: =E8-D9 -> 6224300 | F9: =D9/'04_Actual_Production_&_Costs'!$F$4 -> 0.3859375 | G9: =D9/$E$5 -> 0.0060539216 | H9: =IF(D9>=0,"Favourable (F)","Adverse (A)") -> Favourable (F)
A10: LRV-DL1 | B10: Direct Labour Rate Variance — Skilled Moulding Operators | C10: Direct labour | D10: ='05_Variance_Analysis'!F13 -> -15840 | E10: =E9-D10 -> 6240140 | F10: =D10/'04_Actual_Production_&_Costs'!$F$4 -> -0.165 | G10: =D10/$E$5 -> -0.0025882353 | H10: =IF(D10>=0,"Favourable (F)","Adverse (A)") -> Adverse (A)
A11: LRV-DL2 | B11: Direct Labour Rate Variance — Semi-Skilled Assembly Workers | C11: Direct labour | D11: ='05_Variance_Analysis'!F14 -> 24300 | E11: =E10-D11 -> 6215840 | F11: =D11/'04_Actual_Production_&_Costs'!$F$4 -> 0.253125 | G11: =D11/$E$5 -> 0.0039705882 | H11: =IF(D11>=0,"Favourable (F)","Adverse (A)") -> Favourable (F)
A12: LEV-DL1 | B12: Direct Labour Efficiency Variance — Skilled Moulding Operators | C12: Direct labour | D12: ='05_Variance_Analysis'!G13 -> -13200 | E12: =E11-D12 -> 6229040 | F12: =D12/'04_Actual_Production_&_Costs'!$F$4 -> -0.1375 | G12: =D12/$E$5 -> -0.0021568627 | H12: =IF(D12>=0,"Favourable (F)","Adverse (A)") -> Adverse (A)
A13: LEV-DL2 | B13: Direct Labour Efficiency Variance — Semi-Skilled Assembly Workers | C13: Direct labour | D13: ='05_Variance_Analysis'!G14 -> -39900 | E13: =E12-D13 -> 6268940 | F13: =D13/'04_Actual_Production_&_Costs'!$F$4 -> -0.415625 | G13: =D13/$E$5 -> -0.0065196078 | H13: =IF(D13>=0,"Favourable (F)","Adverse (A)") -> Adverse (A)
A14: VOEV | B14: Variable Overhead Expenditure Variance — Power & Utilities Rate | C14: Variable overhead | D14: ='05_Variance_Analysis'!F20 -> -12060 | E14: =E13-D14 -> 6281000 | F14: =D14/'04_Actual_Production_&_Costs'!$F$4 -> -0.125625 | G14: =D14/$E$5 -> -0.0019705882 | H14: =IF(D14>=0,"Favourable (F)","Adverse (A)") -> Adverse (A)
A15: VOEfV | B15: Variable Overhead Volume Variance — Power & Utilities Rate | C15: Variable overhead | D15: ='05_Variance_Analysis'!G20 -> -20250 | E15: =E14-D15 -> 6301250 | F15: =D15/'04_Actual_Production_&_Costs'!$F$4 -> -0.2109375 | G15: =D15/$E$5 -> -0.0033088235 | H15: =IF(D15>=0,"Favourable (F)","Adverse (A)") -> Adverse (A)
A16: FOEV | B16: Fixed Overhead Expenditure Variance — depreciation, demand charges & supervision | C16: Fixed overhead | D16: ='05_Variance_Analysis'!F21 -> -12000 | E16: =E15-D16 -> 6313250 | F16: =D16/'04_Actual_Production_&_Costs'!$F$4 -> -0.125 | G16: =D16/$E$5 -> -0.0019607843 | H16: =IF(D16>=0,"Favourable (F)","Adverse (A)") -> Adverse (A)
A17: FOVV | B17: Fixed Overhead Volume Variance — depreciation, demand charges & supervision | C17: Fixed overhead | D17: ='05_Variance_Analysis'!G21 -> -26400 | E17: =E16-D17 -> 6339650 | F17: =D17/'04_Actual_Production_&_Costs'!$F$4 -> -0.275 | G17: =D17/$E$5 -> -0.0043137255 | H17: =IF(D17>=0,"Favourable (F)","Adverse (A)") -> Adverse (A)
A18: NET-VAR | B18: TOTAL NET MANUFACTURING COST VARIANCE (SUM OF ALL VARIANCES) | C18: Total variance | D18: =SUM(D6:D17) -> -219650 | E18: =E17 -> 6339650 | F18: =D18/'04_Actual_Production_&_Costs'!$F$4 -> -2.2880208 | G18: =D18/$E$5 -> -0.035890523 | H18: =IF(D18>=0,"Favourable (F)","Adverse (A)") -> Adverse (A)
A19: ACT-REC | B19: RECONCILED ACTUAL MANUFACTURING COST (STD COST - NET VARIANCE) | C19: Reconciled cost | D19: 0 | E19: =$E$5-D18 -> 6339650 | F19: =E19/'04_Actual_Production_&_Costs'!$F$4 -> 66.038021 | G19: =E19/$E$5 -> 1.0358905 | H19: Reconciled
A20: ACT-COST | B20: ACTUAL COST PER ACTUAL COST SHEET (04_Actual_Production_&_Costs) | C20: Actual cost | D20: 0 | E20: ='04_Actual_Production_&_Costs'!I18 -> 6339650 | F20: =E20/'04_Actual_Production_&_Costs'!$F$4 -> 66.038021 | G20: =E20/$E$5 -> 1.0358905 | H20: Source total
A21: DIFF-CHK | B21: UNEXPLAINED RECONCILIATION DIFFERENCE (MUST EQUAL ₹0.00) | C21: Control | D21: 0 | E21: =E19-E20 -> 0 | F21: =E21/'04_Actual_Production_&_Costs'!$F$4 -> 0 | G21: =D21/$E$5 -> 0 | H21: =IF(ROUND(ABS(E21),2)=0,"Pass (Reconciled)", "Check Error") -> Pass (Reconciled)
A24: 2. AUTOMATED MODEL CHECKS
A25: Control ID | B25: Audit Control Description | C25: Expected Difference | D25: Calculated Difference (₹) | E25: Control Formula Logic | H25: Audit Verdict
A26: CHK-01 | B26: Material Price + Usage = Total Material Variance | C26: 0 | D26: ='05_Variance_Analysis'!H8-('04_Actual_Production_&_Costs'!F9-'04_Actual_Production_&_Costs'!I9) -> 0 | E26: (MPV + MUV) - (Std DM - Actual DM) | H26: =IF(ROUND(ABS(D26),2)=0,"PASS","CHECK") -> PASS
A27: CHK-02 | B27: Labour Rate + Efficiency = Total Labour Variance | C27: 0 | D27: ='05_Variance_Analysis'!H15-('04_Actual_Production_&_Costs'!F12-'04_Actual_Production_&_Costs'!I12) -> 0 | E27: (LRV + LEV) - (Std DL - Actual DL) | H27: =IF(ROUND(ABS(D27),2)=0,"PASS","CHECK") -> PASS
A28: CHK-03 | B28: Variable OH Expenditure + Volume = Total VMOH Variance | C28: 0 | D28: =('05_Variance_Analysis'!H20)-('04_Actual_Production_&_Costs'!F14-'04_Actual_Production_&_Costs'!I14) -> 0 | E28: (VOEV + VOVV) - (Absorbed VMOH - Actual VMOH) | H28: =IF(ROUND(ABS(D28),2)=0,"PASS","CHECK") -> PASS
A29: CHK-04 | B29: Fixed OH Expenditure + Volume = Total FMOH Variance | C29: 0 | D29: =('05_Variance_Analysis'!F27+'05_Variance_Analysis'!G27)-'05_Variance_Analysis'!G21 -> 0 | E29: (FMOH Cap + FMOH Eff) - FMOH Volume Variance | H29: =IF(ROUND(ABS(D29),2)=0,"PASS","CHECK") -> PASS
A30: CHK-05 | B30: Grand Total Cost Reconciliation (Std Cost - All Variances = Actual Cost) | C30: 0 | D30: =E21 -> 0 | E30: Reconciled Actual Cost (E20) - Ledger Actual Cost (E21) | H30: =IF(ROUND(ABS(D30),2)=0,"PASS","CHECK") -> PASS
B33: RECONCILIATION CHECK | C33: Result (₹)
B34: Standard Cost | C34: =E5 -> 6120000
B35: Actual Cost | C35: =E20 -> 6339650
B36: Difference | C36: =C34-C35 -> -219650
B37: Absolute Variance | C37: =D18 -> -219650
B38: Reconciliation Status | C38: =IF(C36=C37,"Check Passed","Check Failed") -> Check Passed

Sheet 07_Management_Dashboard
A1: Visual KPI Scorecard, Variance Bridge, Per-Pair Cost Breakdown & Corrective Actions
A3: STANDARD COST (96,000 PAIRS) | C3: ACTUAL FACTORY COST (96,000 PAIRS) | E3: TOTAL NET COST VARIANCE (ADVERSE) | G3: RECONCILIATION & CONTROL STATUS
A4: ='06_Reconciliation_&_Controls'!E5 -> 6120000 | C4: ='06_Reconciliation_&_Controls'!E20 -> 6339650 | E4: ='06_Reconciliation_&_Controls'!D18 -> -219650 | G4: ='06_Reconciliation_&_Controls'!H21 -> Pass (Reconciled)
A5: Standard Cost: ₹63.75 / Pair | C5: Actual Cost: ₹66.04 / Pair | E5: Net Overrun: -₹2.29 / Pair (-3.59%) | G5: 5 of 5 Audit Checks Passed (₹0 Diff)
A8: 1. EXECUTIVE COST & VARIANCE SUMMARY BY COST POOL (96,000 PAIRS PRODUCED)
A9: Cost Pool Category | B9: Standard Cost (₹) | C9: Actual Cost Incurred (₹) | D9: Price / Rate / Variance (₹) | E9: Usage / Efficiency / Volume Variance (₹) | F9: Total Net Variance (₹) | G9: Std Cost / Pair (₹) | H9: Actual Cost / Pair (₹)
A10: Direct Materials (EVA & Rubber) | B10: ='05_Variance_Analysis'!C8 -> 3902400 | C10: ='05_Variance_Analysis'!E8 -> 4006700 | D10: ='05_Variance_Analysis'!F8 -> -43700 | E10: ='05_Variance_Analysis'!G8 -> -60600 | F10: =B10-C10 -> -104300 | G10: =B10/'04_Actual_Production_&_Costs'!$F$4 -> 40.65 | H10: =C10/'04_Actual_Production_&_Costs'!$F$4 -> 41.736458
A11: Direct Labour (Moulding & Assembly) | B11: ='05_Variance_Analysis'!C15 -> 1152000 | C11: ='05_Variance_Analysis'!E15 -> 1196640 | D11: ='05_Variance_Analysis'!F15 -> 8460 | E11: ='05_Variance_Analysis'!G15 -> -53100 | F11: =B11-C11 -> -44640 | G11: =B11/'04_Actual_Production_&_Costs'!$F$4 -> 12 | H11: =C11/'04_Actual_Production_&_Costs'!$F$4 -> 12.465
A12: Variable Manufacturing Overhead (Power) | B12: ='05_Variance_Analysis'!C20 -> 432000 | C12: ='05_Variance_Analysis'!E20 -> 464310 | D12: ='05_Variance_Analysis'!F20 -> -12060 | E12: ='05_Variance_Analysis'!G20 -> -20250 | F12: =B12-C12 -> -32310 | G12: =B12/'04_Actual_Production_&_Costs'!$F$4 -> 4.5 | H12: =C12/'04_Actual_Production_&_Costs'!$F$4 -> 4.8365625
A13: Fixed Manufacturing Overhead (Plant) | B13: ='05_Variance_Analysis'!C21 -> 633600 | C13: ='05_Variance_Analysis'!E21 -> 672000 | D13: ='05_Variance_Analysis'!F21 -> -12000 | E13: ='05_Variance_Analysis'!G21 -> -26400 | F13: =B13-C13 -> -38400 | G13: =B13/'04_Actual_Production_&_Costs'!$F$4 -> 6.6 | H13: =C13/'04_Actual_Production_&_Costs'!$F$4 -> 7
A14: Total Factory Cost & Variances | B14: =SUM(B10:B13) -> 6120000 | C14: =SUM(C10:C13) -> 6339650 | D14: =SUM(D10:D13) -> -59300 | E14: =SUM(E10:E13) -> -160350 | F14: =SUM(F10:F13) -> -219650 | G14: =SUM(G10:G13) -> 63.75 | H14: =SUM(H10:H13) -> 66.038021
A33: 2. INTERPRETATION, ROOT-CAUSE RANKING & CORRECTIVE ACTIONS
A34: Priority Rank | B34: Variance Component | C34: Variance Amount (₹) | D34: Per-Pair Impact (₹/Pair) | E34: Root Cause Identified | G34: Recommended Corrective Action
A35: Priority 1 | B35: Rubber Price Variance | C35: ='06_Reconciliation_&_Controls'!D8 -> -109850 | D35: =C35/'04_Actual_Production_&_Costs'!$F$4 -> -1.1442708 | E35: Actual price was ₹208/kg vs standard ₹195/kg. The ₹13/kg increase on 8,450 kg resulted in the adverse variance. | G35: Compare supplier prices and negotiate better rates.
A37: Priority 2 | B37: EVA usage Variance | C37: ='06_Reconciliation_&_Controls'!D7 -> -97650 | D37: =C37/'04_Actual_Production_&_Costs'!$F$4 -> -1.0171875 | E37: Standard allowed 21,120 kg; actual usage was 22,050 kg. The extra 930 kg at ₹105/kg caused the variance. | G37: Check material issue and scrap records to find where excess usage occurred.
A39: Priority 3 | B39: Semi-Skilled Labour (DL-2) Efficiency Variance | C39: ='06_Reconciliation_&_Controls'!D13 -> -39900 | D39: =C39/'04_Actual_Production_&_Costs'!$F$4 -> -0.415625 | E39: Standard allowed 7,680 hours; actual hours were 8,100. The extra 420 hours at ₹95/hour caused the variance. | G39: Review production delays and identify ways to reduce avoidable hours.
A41: Priority 4 | B41: Fixed Overhead Volume Variance | C41: ='06_Reconciliation_&_Controls'!D17 -> -26400 | D41: =C41/'04_Actual_Production_&_Costs'!$F$4 -> -0.275 | E41: Fixed overhead was absorbed for 11,520 standard hours vs 12,000 budgeted hours. The 480-hour shortfall at ₹55/hour caused the adverse variance | G41: Review the production shortfall and improve production planning where possible.
A43: Priority 5 | B43: Variable Overhead (Power)Volume Variance | C43: ='06_Reconciliation_&_Controls'!D15 -> -20250 | D43: =C43/'04_Actual_Production_&_Costs'!$F$4 -> -0.2109375 | E43: Standard allowed 11,520 hours; actual hours were 12,060. The extra 540 hours at ₹37.50/hour caused the variance | G43: Investigate excess operating hours and reduce avoidable downtime.
